imcflibs/__init__.py
imcflibs/_jython_compat.py
imcflibs/imagej/__init__.py
imcflibs/imagej/_loci.py
imcflibs/imagej/bdv.py
imcflibs/imagej/bioformats.py
imcflibs/imagej/gpu.py
imcflibs/imagej/labelimage.py
imcflibs/imagej/misc.py
imcflibs/imagej/objects3d.py
imcflibs/imagej/omerotools.py
imcflibs/imagej/prefs.py
imcflibs/imagej/processing.py
imcflibs/imagej/projections.py
imcflibs/imagej/resultstable.py
imcflibs/imagej/roimanager.py
imcflibs/imagej/shading.py
imcflibs/imagej/sjlog.py
imcflibs/imagej/split.py
imcflibs/imagej/stitching.py
imcflibs/imagej/trackmate.py
imcflibs/iotools.py
imcflibs/log.py
imcflibs/pathtools.py
imcflibs/strtools.py
imcflibs-1.5.0.dist-info/LICENSE.txt
imcflibs-1.5.0.dist-info/METADATA
imcflibs-1.5.0.dist-info/WHEEL
imcflibs-1.5.0.dist-info/RECORD
