Metadata-Version: 2.3
Name: imcflibs
Version: 1.5.0
Summary: Mostly ImageJ/Fiji-related Python helper functions.
License: GPL-3.0-or-later
Author: Niko Ehrenfeuchter
Author-email: nikolaus.ehrenfeuchter@unibas.ch
Requires-Python: >=2.7
Classifier: License :: OSI Approved :: GNU General Public License v3 or later (GPLv3+)
Classifier: Programming Language :: Python :: 2
Classifier: Programming Language :: Python :: 2.7
Classifier: Programming Language :: Python :: 3
Classifier: Programming Language :: Python :: 3.4
Classifier: Programming Language :: Python :: 3.5
Classifier: Programming Language :: Python :: 3.6
Classifier: Programming Language :: Python :: 3.7
Classifier: Programming Language :: Python :: 3.8
Classifier: Programming Language :: Python :: 3.9
Classifier: Programming Language :: Python :: 3.10
Classifier: Programming Language :: Python :: 3.11
Classifier: Programming Language :: Python :: 3.12
Classifier: Programming Language :: Python :: 3.13
Requires-Dist: imcf-fiji-mocks (>=0.10.0)
Requires-Dist: python-micrometa (>=15.2.2,<16.0.0)
Requires-Dist: sjlogging (>=0.5.2)
Project-URL: Documentation, https://imcf.one/apidocs/imcflibs/imcflibs.html
Project-URL: Repository, https://github.com/imcf/python-imcflibs
